vc2_bit_widths/__init__.py
vc2_bit_widths/bundle.py
vc2_bit_widths/fast_fractions.py
vc2_bit_widths/fast_partial_analyse_quantise_synthesise.py
vc2_bit_widths/fast_partial_analysis_transform.py
vc2_bit_widths/helpers.py
vc2_bit_widths/infinite_arrays.py
vc2_bit_widths/json_serialisations.py
vc2_bit_widths/linexp.py
vc2_bit_widths/pattern_evaluation.py
vc2_bit_widths/pattern_generation.py
vc2_bit_widths/pattern_optimisation.py
vc2_bit_widths/patterns.py
vc2_bit_widths/picture_packing.py
vc2_bit_widths/pyexp.py
vc2_bit_widths/quantisation.py
vc2_bit_widths/signal_bounds.py
vc2_bit_widths/vc2_filters.py
vc2_bit_widths/version.py
vc2_bit_widths/scripts/__init__.py
vc2_bit_widths/scripts/argument_parsers.py
vc2_bit_widths/scripts/loader_utils.py
vc2_bit_widths/scripts/vc2_bit_width_test_pictures.py
vc2_bit_widths/scripts/vc2_bit_widths_table.py
vc2_bit_widths/scripts/vc2_bundle.py
vc2_bit_widths/scripts/vc2_maximum_quantisation_index.py
vc2_bit_widths/scripts/vc2_optimise_synthesis_test_patterns.py
vc2_bit_widths/scripts/vc2_static_filter_analysis.py
vc2_bit_widths/scripts/vc2_static_filter_analysis_combine.py
vc2_bit_widths-1.0.0.dist-info/LICENSE.txt
vc2_bit_widths-1.0.0.dist-info/METADATA
vc2_bit_widths-1.0.0.dist-info/WHEEL
vc2_bit_widths-1.0.0.dist-info/entry_points.txt
vc2_bit_widths-1.0.0.dist-info/top_level.txt
vc2_bit_widths-1.0.0.dist-info/RECORD
